README.md
setup.cfg
setup.py
bin/peri
peri/__init__.py
peri/conf.py
peri/fft.py
peri/initializers.py
peri/interpolation.py
peri/logger.py
peri/logger_colors.py
peri/main.py
peri/models.py
peri/runner.py
peri/special.py
peri/states.py
peri/util.py
peri.egg-info/PKG-INFO
peri.egg-info/SOURCES.txt
peri.egg-info/dependency_links.txt
peri.egg-info/requires.txt
peri.egg-info/top_level.txt
peri/../README.md
peri/comp/__init__.py
peri/comp/comp.py
peri/comp/exactpsf.py
peri/comp/ilms.py
peri/comp/objs.py
peri/comp/psfcalc.py
peri/comp/psfs.py
peri/gui/__init__.py
peri/gui/interface.py
peri/gui/main.ui
peri/gui/model-builder.ui
peri/mc/__init__.py
peri/mc/engines.py
peri/mc/observers.py
peri/mc/sample.py
peri/mc/samplers.py
peri/opt/__init__.py
peri/opt/addsubtract.py
peri/opt/optimize.py
peri/opt/opttest.py
peri/opt/scalar.py
peri/opt/tiling.py
peri/priors/__init__.py
peri/priors/overlap.py
peri/priors/priors.py
peri/test/__init__.py
peri/test/analyze.py
peri/test/init.py
peri/test/nbody.py
peri/test/parallel.py
peri/test/simulation.py
peri/test/track.py
peri/viz/__init__.py
peri/viz/base.py
peri/viz/ilmplots.py
peri/viz/interaction.py
peri/viz/plots.py
peri/viz/render.py