Metadata-Version: 1.1
Name: peri
Version: 0.1.3
Summary: Parameter Extraction from the Reconstruction of Images
Home-page: http://github.com/peri-source/peri/
Author: Matt Bierbaum, Brian Leahy
Author-email: UNKNOWN
License: MIT License
Platform: any
Classifier: Programming Language :: Python :: 2.6
Classifier: Programming Language :: Python :: 2.7
Classifier: Programming Language :: Python :: 3
Classifier: Development Status :: 2 - Pre-Alpha
Classifier: Natural Language :: English
Classifier: Intended Audience :: Developers
Classifier: Intended Audience :: Science/Research
Classifier: License :: OSI Approved :: MIT License
Classifier: Operating System :: OS Independent
Classifier: Topic :: Scientific/Engineering :: Image Recognition
Classifier: Topic :: Scientific/Engineering :: Physics
